{
  "config": "{\"version\":\"5.59\",\"themeCollection\":{\"baseTheme\":{\"name\":\"CY24SU10\",\"version\":\"5.60\",\"type\":2}},\"activeSectionIndex\":0,\"defaultDrillFilterOtherVisuals\":true,\"slowDataSourceSettings\":{\"isCrossHighlightingDisabled\":false,\"isSlicerSelectionsButtonEnabled\":false,\"isFilterSelectionsButtonEnabled\":false,\"isFieldWellButtonEnabled\":false,\"isApplyAllButtonEnabled\":false},\"linguisticSchemaSyncVersion\":2,\"settings\":{\"useNewFilterPaneExperience\":true,\"allowChangeFilterTypes\":true,\"useStylableVisualContainerHeader\":true,\"queryLimitOption\":6,\"useEnhancedTooltips\":true,\"exportDataMode\":1,\"useDefaultAggregateDisplayName\":true},\"objects\":{\"section\":[{\"properties\":{\"verticalAlignment\":{\"expr\":{\"Literal\":{\"Value\":\"'Top'\"}}}}}]}}",
  "layoutOptimization": 0,
  "resourcePackages": [
    {
      "resourcePackage": {
        "disabled": false,
        "items": [
          {
            "name": "CY24SU10",
            "path": "BaseThemes/CY24SU10.json",
            "type": 202
          }
        ],
        "name": "SharedResources",
        "type": 2
      }
    }
  ],
  "sections": [
    {
      "config": "{}",
      "displayName": "Page 1",
      "displayOption": 1,
      "filters": "[]",
      "height": 720.00,
      "name": "c3db846d090bc9d00539",
      "visualContainers": [
        {
          "config": "{\"name\":\"19e1f3577703a35e2169\",\"layouts\":[{\"id\":0,\"position\":{\"x\":411.4810562571757,\"y\":346.0849598163031,\"z\":2,\"width\":413.6854190585534,\"height\":189.5752009184845,\"tabOrder\":2}}],\"singleVisual\":{\"visualType\":\"barChart\",\"projections\":{\"Y\":[{\"queryRef\":\"_Measure.Sales\"}],\"Category\":[{\"queryRef\":\"Product.Category\",\"active\":true}]},\"prototypeQuery\":{\"Version\":2,\"From\":[{\"Name\":\"_\",\"Entity\":\"_Measure\",\"Type\":0},{\"Name\":\"p\",\"Entity\":\"Product\",\"Type\":0}],\"Select\":[{\"Measure\":{\"Expression\":{\"SourceRef\":{\"Source\":\"_\"}},\"Property\":\"Sales\"},\"Name\":\"_Measure.Sales\",\"NativeReferenceName\":\"Sales\"},{\"Column\":{\"Expression\":{\"SourceRef\":{\"Source\":\"p\"}},\"Property\":\"Category\"},\"Name\":\"Product.Category\",\"NativeReferenceName\":\"Category\"}],\"OrderBy\":[{\"Direction\":2,\"Expression\":{\"Measure\":{\"Expression\":{\"SourceRef\":{\"Source\":\"_\"}},\"Property\":\"Sales\"}}}]},\"drillFilterOtherVisuals\":true,\"hasDefaultSort\":true}}",
          "filters": "[]",
          "height": 189.58,
          "width": 413.69,
          "x": 411.48,
          "y": 346.08,
          "z": 2.00
        },
        {
          "config": "{\"name\":\"8778c4d55c7bbf65c5be\",\"layouts\":[{\"id\":0,\"position\":{\"x\":0,\"y\":0,\"z\":1,\"width\":1280,\"height\":354.1676234213548,\"tabOrder\":1}}],\"singleVisual\":{\"visualType\":\"lineChart\",\"projections\":{\"Y\":[{\"queryRef\":\"_Measure.Sales\"}],\"Category\":[{\"queryRef\":\"Date.Year\",\"active\":true},{\"queryRef\":\"Date.Month\",\"active\":true}]},\"prototypeQuery\":{\"Version\":2,\"From\":[{\"Name\":\"_\",\"Entity\":\"_Measure\",\"Type\":0},{\"Name\":\"d\",\"Entity\":\"Date\",\"Type\":0}],\"Select\":[{\"Measure\":{\"Expression\":{\"SourceRef\":{\"Source\":\"_\"}},\"Property\":\"Sales\"},\"Name\":\"_Measure.Sales\",\"NativeReferenceName\":\"Sales\"},{\"Column\":{\"Expression\":{\"SourceRef\":{\"Source\":\"d\"}},\"Property\":\"Year\"},\"Name\":\"Date.Year\",\"NativeReferenceName\":\"Year\"},{\"Column\":{\"Expression\":{\"SourceRef\":{\"Source\":\"d\"}},\"Property\":\"Month\"},\"Name\":\"Date.Month\",\"NativeReferenceName\":\"Month\"}]},\"drillFilterOtherVisuals\":true,\"objects\":{\"categoryAxis\":[{\"properties\":{\"concatenateLabels\":{\"expr\":{\"Literal\":{\"Value\":\"false\"}}},\"show\":{\"expr\":{\"Literal\":{\"Value\":\"true\"}}}}}]}}}",
          "filters": "[]",
          "height": 354.17,
          "width": 1280.00,
          "x": 0.00,
          "y": 0.00,
          "z": 1.00
        },
        {
          "config": "{\"name\":\"f7b5066bc6aaf33829aa\",\"layouts\":[{\"id\":0,\"position\":{\"x\":0,\"y\":340.94144661308843,\"z\":0,\"width\":429.1159586681975,\"height\":379.150401836969,\"tabOrder\":0}}],\"singleVisual\":{\"visualType\":\"tableEx\",\"projections\":{\"Values\":[{\"queryRef\":\"Product.Image product\"},{\"queryRef\":\"Product.Product\"},{\"queryRef\":\"_Measure.Quantity\"},{\"queryRef\":\"_Measure.Sales\"}]},\"prototypeQuery\":{\"Version\":2,\"From\":[{\"Name\":\"p\",\"Entity\":\"Product\",\"Type\":0},{\"Name\":\"_\",\"Entity\":\"_Measure\",\"Type\":0}],\"Select\":[{\"Column\":{\"Expression\":{\"SourceRef\":{\"Source\":\"p\"}},\"Property\":\"Product\"},\"Name\":\"Product.Product\",\"NativeReferenceName\":\"Product\"},{\"Column\":{\"Expression\":{\"SourceRef\":{\"Source\":\"p\"}},\"Property\":\"Image product\"},\"Name\":\"Product.Image product\",\"NativeReferenceName\":\"Image\"},{\"Measure\":{\"Expression\":{\"SourceRef\":{\"Source\":\"_\"}},\"Property\":\"Sales\"},\"Name\":\"_Measure.Sales\",\"NativeReferenceName\":\"Total Sales\"},{\"Measure\":{\"Expression\":{\"SourceRef\":{\"Source\":\"_\"}},\"Property\":\"Quantity\"},\"Name\":\"_Measure.Quantity\",\"NativeReferenceName\":\"Quantity\"}],\"OrderBy\":[{\"Direction\":2,\"Expression\":{\"Column\":{\"Expression\":{\"SourceRef\":{\"Source\":\"p\"}},\"Property\":\"Image product\"}}}]},\"columnProperties\":{\"_Measure.Sales\":{\"displayName\":\"Total Sales\"},\"Product.Image product\":{\"displayName\":\"Image\"}},\"drillFilterOtherVisuals\":true,\"objects\":{\"grid\":[{\"properties\":{\"imageHeight\":{\"expr\":{\"Literal\":{\"Value\":\"25D\"}}}}}]},\"vcObjects\":{\"title\":[{\"properties\":{\"show\":{\"expr\":{\"Literal\":{\"Value\":\"false\"}}}}}]}}}",
          "filters": "[]",
          "height": 379.15,
          "width": 429.12,
          "x": 0.00,
          "y": 340.94,
          "z": 0.00
        }
      ],
      "width": 1280.00
    }
  ]
}